[
  {
    "version": "20260503.3",
    "url": "bundle-20260503.3.zip",
    "hash": "4ddafab6c369fd5199169442f4426631d7cd428c08b4f8b0a4fc6451bdd5066f",
    "minNativeVersion": null,
    "notes": "- feat: 添加标签输入功能到批量编辑表单，支持标签替换功能\n  Co-authored-by: Copilot <copilot@github.com>",
    "updateLevel": "silent",
    "publishedAt": "2026-05-03T05:39:34Z"
  },
  {
    "version": "20260503.2",
    "url": "bundle-20260503.2.zip",
    "hash": "ccb430f277ee4fc0196bd94a4fbe60eb02ae5a176f50de78fce96aa700ddb6c3",
    "minNativeVersion": null,
    "notes": "- feat: 优化备注功能，添加 Markdown 检测和复制功能",
    "updateLevel": "silent",
    "publishedAt": "2026-05-03T05:12:49Z"
  },
  {
    "version": "20260503.1",
    "url": "bundle-20260503.1.zip",
    "hash": "f73dd6ae4fb0db71c97ff0baf037e851b921e84a78ea0c7e777ab46912c373f3",
    "minNativeVersion": null,
    "notes": "- feat: 添加标签输入功能到批量编辑表单，优化数据管理\n\n- feat: 添加 Markdown 支持，优化备注输入和预览功能\n  Co-authored-by: Copilot <copilot@github.com>",
    "updateLevel": "silent",
    "publishedAt": "2026-05-03T03:21:06Z"
  }
]